cookiecutterJSROBIN888/__init__.py
cookiecutterJSROBIN888/__main__.py
cookiecutterJSROBIN888/cli.py
cookiecutterJSROBIN888-0.0.0.dist-info/AUTHORS.rst
cookiecutterJSROBIN888-0.0.0.dist-info/LICENSE
cookiecutterJSROBIN888-0.0.0.dist-info/METADATA
cookiecutterJSROBIN888-0.0.0.dist-info/WHEEL
cookiecutterJSROBIN888-0.0.0.dist-info/entry_points.txt
cookiecutterJSROBIN888-0.0.0.dist-info/top_level.txt
cookiecutterJSROBIN888-0.0.0.dist-info/RECORD
