Metadata-Version: 2.1
Name: cookiecutterJSROBIN888
Version: 0.0.0
Summary: An example package. Generated with cookiecutter-pylibrary.
Home-page: https://github.com/jsrobin888/cookiecutterJSROBIN888
Author: robin liu
Author-email: robin.liu.uw@gmail.com
License: BSD 2-Clause License
Project-URL: Documentation, https://cookiecutterJSROBIN888.readthedocs.io/
Project-URL: Changelog, https://cookiecutterJSROBIN888.readthedocs.io/en/latest/changelog.html
Project-URL: Issue Tracker, https://github.com/jsrobin888/cookiecutterJSROBIN888/issues
Platform: UNKNOWN
Classifier: Development Status :: 5 - Production/Stable
Classifier: Intended Audience :: Developers
Classifier: License :: OSI Approved :: BSD License
Classifier: Operating System :: Unix
Classifier: Operating System :: POSIX
Classifier: Operating System :: Microsoft :: Windows
Classifier: Programming Language :: Python
Classifier: Programming Language :: Python :: 2.7
Classifier: Programming Language :: Python :: 3
Classifier: Programming Language :: Python :: 3.4
Classifier: Programming Language :: Python :: 3.5
Classifier: Programming Language :: Python :: 3.6
Classifier: Programming Language :: Python :: 3.7
Classifier: Programming Language :: Python :: Implementation :: CPython
Classifier: Programming Language :: Python :: Implementation :: PyPy
Classifier: Topic :: Utilities
Requires-Python: >=2.7, !=3.0.*, !=3.1.*, !=3.2.*, !=3.3.*
